ptc/__init__.py
ptc/ptc.py
ptc/rotation.py
ptc/sphere.py
ptc/types.py
test/__init__.py
test/calibration_test.py
test/conftest.py
test/sphere_test.py
ptc-0.0.1.dev20200721152952.dist-info/LICENSE
ptc-0.0.1.dev20200721152952.dist-info/METADATA
ptc-0.0.1.dev20200721152952.dist-info/WHEEL
ptc-0.0.1.dev20200721152952.dist-info/top_level.txt
ptc-0.0.1.dev20200721152952.dist-info/RECORD
