Metadata-Version: 2.1
Name: ptc
Version: 0.0.1.dev20200721152952
Summary: Pulse Tool Calibration library
Home-page: https://rozum.com
Author: Rozum Robotics
Author-email: dev@rozum.com
License: Apache License 2.0
Platform: UNKNOWN
Classifier: License :: OSI Approved :: Apache Software License
Classifier: Development Status :: 4 - Beta
Classifier: Programming Language :: Python
Classifier: Programming Language :: Python :: 3
Classifier: Programming Language :: Python :: Implementation :: CPython
Requires-Python: >=3.5
Requires-Dist: numpy (==1.18.1)
Requires-Dist: scipy (==1.4.1)
